Workbook

Sheet Leeme
B1: Hoja para apartar IVA e IRPF
B2: Herramienta de estimación para autónomos que empiezan. No es asesoramiento fiscal: confirma tu caso con una gestoría o el PAE.
B3: Cómo se usa (3 pasos)
B4: 1. En la hoja «Ajustes» revisa el año, el IVA (21 %), el % del modelo 130 (20 %) y si presentas el modelo 130.
B5: 2. Cada vez que emitas una factura, apúntala en «Facturas» (solo las celdas amarillas). Verás al momento cuánto apartar de IVA e IRPF y cuánto queda libre.
B6: 3. Apunta tus gastos (cuota de autónomos, dominio, herramientas) en «Gastos». La hoja «Trimestres» calcula lo que ingresarías en Hacienda cada trimestre.
B7: Colores
B8: Celdas amarillas con letra azul = las rellenas tú. Celdas blancas con letra negra = fórmulas (no las toques).
B9: Las filas marcadas «EJEMPLO» son de muestra: bórralas o sobrescríbelas con tus datos.
B10: Qué calcula y con qué supuestos
B11: • IVA: 21 % de la base imponible (tipo general). Es dinero que cobras al cliente pero no es tuyo: lo ingresas cada trimestre (modelo 303) restando el IVA que hayas pagado en gastos.
B12: • Retención de IRPF: solo si facturas a empresas o autónomos y según tu epígrafe del IAE. Orientativamente 7 % (primeros 3 años de actividad) o 15 % (general). A un cliente particular no se le aplica.
... B21: Los porcentajes son los vigentes cuando se creó la hoja; si cambian, edítalos en «Ajustes».

Sheet Ajustes
A1: Ajustes
A3: Año que estás registrando | B3: 2026 | C3: Cambia el año al empezar uno nuevo (o copia el archivo).
A4: IVA general | B4: 0.21 | C4: Tipo general en España.
A5: Pago fraccionado modelo 130 (% del beneficio) | B5: 0.2 | C5: 20 % del rendimiento neto acumulado.
A6: ¿Presentas el modelo 130? (Sí/No) | B6: Sí | C6: «No» solo si ≥70 % de tus ingresos del año anterior llevó retención. Confírmalo con tu gestoría.
A8: Retenciones posibles en factura
A9: Sin retención (cliente particular) | B9: 0 | C9: Se usan en la lista desplegable de «Facturas». Pregunta a tu gestoría cuál te corresponde.
A10: Nuevo autónomo (primeros 3 años) | B10: 0.07
A11: General (profesional) | B11: 0.15
A13: Servicios y precio de lanzamiento (€, sin IVA)
A14: Web con galería y reservas | B14: 350 | C14: Precios del flyer, solo de referencia (se usan en la lista desplegable de «Facturas»).
A15: Asistente de WhatsApp | B15: 250
A16: Tienda online pequeña | B16: 550
A17: Google Maps y SEO local | B17: 150
A18: Pack web + reservas + WhatsApp | B18: 550
A19: Mantenimiento mensual | B19: 20
A20: Otro

Sheet Facturas
A1: Facturas emitidas
A2: Rellena solo las celdas amarillas. Cada fila calcula cuánto apartar de IVA e IRPF.
A4: TOTALES | E4: =SUM(E6:E205) -> 350 | G4: =SUM(G6:G205) -> 73.5 | H4: =SUM(H6:H205) -> 24.5 | I4: =SUM(I6:I205) -> 399 | J4: =SUM(J6:J205) -> 45.5 | K4: =SUM(K6:K205) -> 119 | L4: =SUM(L6:L205) -> 280
A5: Fecha | B5: Nº factura | C5: Cliente | D5: Servicio | E5: Base imponible (€, sin IVA) | F5: Retención IRPF % | G5: IVA (€) | H5: Retención (€) | I5: Total que paga el cliente (€) | J5: IRPF a apartar (€) | K5: TOTAL a apartar: IVA + IRPF (€) | L5: Libre para ti, antes de gastos (€) | M5: Año | N5: Trim.
A6: 46310 | B6: 2026-001 | C6: Cliente EJEMPLO (bórrame) | D6: Web con galería y reservas | E6: 350 | F6: 0.07 | G6: =IF($E6="","",ROUND($E6*Ajustes!$B$4,2)) -> 73.5 | H6: =IF($E6="","",ROUND($E6*N($F6),2)) -> 24.5 | I6: =IF($E6="","",$E6+$G6-$H6) -> 399 | J6: =IF($E6="","",IF(Ajustes!$B$6="Sí",MAX(0,ROUND($E6*Ajustes!$B$5-$H6,2)),0)) -> 45.5 | K6: =IF($E6="","",$G6+$J6) -> 119 | L6: =IF($E6="","",$I6-$K6) -> 280 | M6: =IF($A6="","",YEAR($A6)) -> 2026 | N6: =IF($A6="","",ROUNDUP(MONTH($A6)/3,0)) -> 4
G7: =IF($E7="","",ROUND($E7*Ajustes!$B$4,2)) | H7: =IF($E7="","",ROUND($E7*N($F7),2)) | I7: =IF($E7="","",$E7+$G7-$H7) | J7: =IF($E7="","",IF(Ajustes!$B$6="Sí",MAX(0,ROUND($E7*Ajustes!$B$5-$H7,2)),0)) | K7: =IF($E7="","",$G7+$J7) | L7: =IF($E7="","",$I7-$K7) | M7: =IF($A7="","",YEAR($A7)) | N7: =IF($A7="","",ROUNDUP(MONTH($A7)/3,0))
G8: =IF($E8="","",ROUND($E8*Ajustes!$B$4,2)) | H8: =IF($E8="","",ROUND($E8*N($F8),2)) | I8: =IF($E8="","",$E8+$G8-$H8) | J8: =IF($E8="","",IF(Ajustes!$B$6="Sí",MAX(0,ROUND($E8*Ajustes!$B$5-$H8,2)),0)) | K8: =IF($E8="","",$G8+$J8) | L8: =IF($E8="","",$I8-$K8) | M8: =IF($A8="","",YEAR($A8)) | N8: =IF($A8="","",ROUNDUP(MONTH($A8)/3,0))
G9: =IF($E9="","",ROUND($E9*Ajustes!$B$4,2)) | H9: =IF($E9="","",ROUND($E9*N($F9),2)) | I9: =IF($E9="","",$E9+$G9-$H9) | J9: =IF($E9="","",IF(Ajustes!$B$6="Sí",MAX(0,ROUND($E9*Ajustes!$B$5-$H9,2)),0)) | K9: =IF($E9="","",$G9+$J9) | L9: =IF($E9="","",$I9-$K9) | M9: =IF($A9="","",YEAR($A9)) | N9: =IF($A9="","",ROUNDUP(MONTH($A9)/3,0))
G10: =IF($E10="","",ROUND($E10*Ajustes!$B$4,2)) | H10: =IF($E10="","",ROUND($E10*N($F10),2)) | I10: =IF($E10="","",$E10+$G10-$H10) | J10: =IF($E10="","",IF(Ajustes!$B$6="Sí",MAX(0,ROUND($E10*Ajustes!$B$5-$H10,2)),0)) | K10: =IF($E10="","",$G10+$J10) | L10: =IF($E10="","",$I10-$K10) | M10: =IF($A10="","",YEAR($A10)) | N10: =IF($A10="","",ROUNDUP(MONTH($A10)/3,0))
G11: =IF($E11="","",ROUND($E11*Ajustes!$B$4,2)) | H11: =IF($E11="","",ROUND($E11*N($F11),2)) | I11: =IF($E11="","",$E11+$G11-$H11) | J11: =IF($E11="","",IF(Ajustes!$B$6="Sí",MAX(0,ROUND($E11*Ajustes!$B$5-$H11,2)),0)) | K11: =IF($E11="","",$G11+$J11) | L11: =IF($E11="","",$I11-$K11) | M11: =IF($A11="","",YEAR($A11)) | N11: =IF($A11="","",ROUNDUP(MONTH($A11)/3,0))
G12: =IF($E12="","",ROUND($E12*Ajustes!$B$4,2)) | H12: =IF($E12="","",ROUND($E12*N($F12),2)) | I12: =IF($E12="","",$E12+$G12-$H12) | J12: =IF($E12="","",IF(Ajustes!$B$6="Sí",MAX(0,ROUND($E12*Ajustes!$B$5-$H12,2)),0)) | K12: =IF($E12="","",$G12+$J12) | L12: =IF($E12="","",$I12-$K12) | M12: =IF($A12="","",YEAR($A12)) | N12: =IF($A12="","",ROUNDUP(MONTH($A12)/3,0))
G13: =IF($E13="","",ROUND($E13*Ajustes!$B$4,2)) | H13: =IF($E13="","",ROUND($E13*N($F13),2)) | I13: =IF($E13="","",$E13+$G13-$H13) | J13: =IF($E13="","",IF(Ajustes!$B$6="Sí",MAX(0,ROUND($E13*Ajustes!$B$5-$H13,2)),0)) | K13: =IF($E13="","",$G13+$J13) | L13: =IF($E13="","",$I13-$K13) | M13: =IF($A13="","",YEAR($A13)) | N13: =IF($A13="","",ROUNDUP(MONTH($A13)/3,0))
G14: =IF($E14="","",ROUND($E14*Ajustes!$B$4,2)) | H14: =IF($E14="","",ROUND($E14*N($F14),2)) | I14: =IF($E14="","",$E14+$G14-$H14) | J14: =IF($E14="","",IF(Ajustes!$B$6="Sí",MAX(0,ROUND($E14*Ajustes!$B$5-$H14,2)),0)) | K14: =IF($E14="","",$G14+$J14) | L14: =IF($E14="","",$I14-$K14) | M14: =IF($A14="","",YEAR($A14)) | N14: =IF($A14="","",ROUNDUP(MONTH($A14)/3,0))
G15: =IF($E15="","",ROUND($E15*Ajustes!$B$4,2)) | H15: =IF($E15="","",ROUND($E15*N($F15),2)) | I15: =IF($E15="","",$E15+$G15-$H15) | J15: =IF($E15="","",IF(Ajustes!$B$6="Sí",MAX(0,ROUND($E15*Ajustes!$B$5-$H15,2)),0)) | K15: =IF($E15="","",$G15+$J15) | L15: =IF($E15="","",$I15-$K15) | M15: =IF($A15="","",YEAR($A15)) | N15: =IF($A15="","",ROUNDUP(MONTH($A15)/3,0))
G16: =IF($E16="","",ROUND($E16*Ajustes!$B$4,2)) | H16: =IF($E16="","",ROUND($E16*N($F16),2)) | I16: =IF($E16="","",$E16+$G16-$H16) | J16: =IF($E16="","",IF(Ajustes!$B$6="Sí",MAX(0,ROUND($E16*Ajustes!$B$5-$H16,2)),0)) | K16: =IF($E16="","",$G16+$J16) | L16: =IF($E16="","",$I16-$K16) | M16: =IF($A16="","",YEAR($A16)) | N16: =IF($A16="","",ROUNDUP(MONTH($A16)/3,0))
G17: =IF($E17="","",ROUND($E17*Ajustes!$B$4,2)) | H17: =IF($E17="","",ROUND($E17*N($F17),2)) | I17: =IF($E17="","",$E17+$G17-$H17) | J17: =IF($E17="","",IF(Ajustes!$B$6="Sí",MAX(0,ROUND($E17*Ajustes!$B$5-$H17,2)),0)) | K17: =IF($E17="","",$G17+$J17) | L17: =IF($E17="","",$I17-$K17) | M17: =IF($A17="","",YEAR($A17)) | N17: =IF($A17="","",ROUNDUP(MONTH($A17)/3,0))
G18: =IF($E18="","",ROUND($E18*Ajustes!$B$4,2)) | H18: =IF($E18="","",ROUND($E18*N($F18),2)) | I18: =IF($E18="","",$E18+$G18-$H18) | J18: =IF($E18="","",IF(Ajustes!$B$6="Sí",MAX(0,ROUND($E18*Ajustes!$B$5-$H18,2)),0)) | K18: =IF($E18="","",$G18+$J18) | L18: =IF($E18="","",$I18-$K18) | M18: =IF($A18="","",YEAR($A18)) | N18: =IF($A18="","",ROUNDUP(MONTH($A18)/3,0))
... G205: =IF($E205="","",ROUND($E205*Ajustes!$B$4,2)) | H205: =IF($E205="","",ROUND($E205*N($F205),2)) | I205: =IF($E205="","",$E205+$G205-$H205) | J205: =IF($E205="","",IF(Ajustes!$B$6="Sí",MAX(0,ROUND($E205*Ajustes!$B$5-$H205,2)),0)) | K205: =IF($E205="","",$G205+$J205) | L205: =IF($E205="","",$I205-$K205) | M205: =IF($A205="","",YEAR($A205)) | N205: =IF($A205="","",ROUNDUP(MONTH($A205)/3,0))

Sheet Gastos
A1: Gastos del negocio
A2: Cuota de autónomos, dominio, herramientas… La cuota de autónomos no lleva IVA (pon 0).
A4: TOTALES | D4: =SUM(D6:D205) -> 92 | E4: =SUM(E6:E205) -> 2.52 | G4: =SUM(G6:G205) -> 94.52
A5: Fecha | B5: Concepto | C5: Proveedor | D5: Base (€, sin IVA) | E5: IVA soportado (€) | F5: ¿Deducible? (Sí/No) | G5: Total pagado (€) | H5: Año | I5: Trim.
A6: 46296 | B6: Cuota de autónomos EJEMPLO (bórrame) | C6: Seguridad Social | D6: 80 | E6: 0 | F6: Sí | G6: =IF($D6="","",$D6+N($E6)) -> 80 | H6: =IF($A6="","",YEAR($A6)) -> 2026 | I6: =IF($A6="","",ROUNDUP(MONTH($A6)/3,0)) -> 4
A7: 46300 | B7: Dominio EJEMPLO (bórrame) | C7: Registrador | D7: 12 | E7: 2.52 | F7: Sí | G7: =IF($D7="","",$D7+N($E7)) -> 14.52 | H7: =IF($A7="","",YEAR($A7)) -> 2026 | I7: =IF($A7="","",ROUNDUP(MONTH($A7)/3,0)) -> 4
G8: =IF($D8="","",$D8+N($E8)) | H8: =IF($A8="","",YEAR($A8)) | I8: =IF($A8="","",ROUNDUP(MONTH($A8)/3,0))
G9: =IF($D9="","",$D9+N($E9)) | H9: =IF($A9="","",YEAR($A9)) | I9: =IF($A9="","",ROUNDUP(MONTH($A9)/3,0))
G10: =IF($D10="","",$D10+N($E10)) | H10: =IF($A10="","",YEAR($A10)) | I10: =IF($A10="","",ROUNDUP(MONTH($A10)/3,0))
G11: =IF($D11="","",$D11+N($E11)) | H11: =IF($A11="","",YEAR($A11)) | I11: =IF($A11="","",ROUNDUP(MONTH($A11)/3,0))
G12: =IF($D12="","",$D12+N($E12)) | H12: =IF($A12="","",YEAR($A12)) | I12: =IF($A12="","",ROUNDUP(MONTH($A12)/3,0))
G13: =IF($D13="","",$D13+N($E13)) | H13: =IF($A13="","",YEAR($A13)) | I13: =IF($A13="","",ROUNDUP(MONTH($A13)/3,0))
G14: =IF($D14="","",$D14+N($E14)) | H14: =IF($A14="","",YEAR($A14)) | I14: =IF($A14="","",ROUNDUP(MONTH($A14)/3,0))
G15: =IF($D15="","",$D15+N($E15)) | H15: =IF($A15="","",YEAR($A15)) | I15: =IF($A15="","",ROUNDUP(MONTH($A15)/3,0))
G16: =IF($D16="","",$D16+N($E16)) | H16: =IF($A16="","",YEAR($A16)) | I16: =IF($A16="","",ROUNDUP(MONTH($A16)/3,0))
G17: =IF($D17="","",$D17+N($E17)) | H17: =IF($A17="","",YEAR($A17)) | I17: =IF($A17="","",ROUNDUP(MONTH($A17)/3,0))
G18: =IF($D18="","",$D18+N($E18)) | H18: =IF($A18="","",YEAR($A18)) | I18: =IF($A18="","",ROUNDUP(MONTH($A18)/3,0))
G19: =IF($D19="","",$D19+N($E19)) | H19: =IF($A19="","",YEAR($A19)) | I19: =IF($A19="","",ROUNDUP(MONTH($A19)/3,0))
... G205: =IF($D205="","",$D205+N($E205)) | H205: =IF($A205="","",YEAR($A205)) | I205: =IF($A205="","",ROUNDUP(MONTH($A205)/3,0))

Sheet Trimestres
A1: Resumen por trimestre
A2: Todo se calcula solo a partir de «Facturas» y «Gastos» para el año indicado en «Ajustes».
A4: Concepto | B4: 1 | C4: 2 | D4: 3 | E4: 4 | F4: Año
A5: Ingresos (base imponible) | B5: =SUMIFS(Facturas!$E$6:$E$205,Facturas!$M$6:$M$205,Ajustes!$B$3,Facturas!$N$6:$N$205,B$4) -> 0 | C5: =SUMIFS(Facturas!$E$6:$E$205,Facturas!$M$6:$M$205,Ajustes!$B$3,Facturas!$N$6:$N$205,C$4) -> 0 | D5: =SUMIFS(Facturas!$E$6:$E$205,Facturas!$M$6:$M$205,Ajustes!$B$3,Facturas!$N$6:$N$205,D$4) -> 0 | E5: =SUMIFS(Facturas!$E$6:$E$205,Facturas!$M$6:$M$205,Ajustes!$B$3,Facturas!$N$6:$N$205,E$4) -> 350 | F5: =SUM(B5:E5) -> 350
A6: IVA cobrado a clientes (repercutido) | B6: =SUMIFS(Facturas!$G$6:$G$205,Facturas!$M$6:$M$205,Ajustes!$B$3,Facturas!$N$6:$N$205,B$4) -> 0 | C6: =SUMIFS(Facturas!$G$6:$G$205,Facturas!$M$6:$M$205,Ajustes!$B$3,Facturas!$N$6:$N$205,C$4) -> 0 | D6: =SUMIFS(Facturas!$G$6:$G$205,Facturas!$M$6:$M$205,Ajustes!$B$3,Facturas!$N$6:$N$205,D$4) -> 0 | E6: =SUMIFS(Facturas!$G$6:$G$205,Facturas!$M$6:$M$205,Ajustes!$B$3,Facturas!$N$6:$N$205,E$4) -> 73.5 | F6: =SUM(B6:E6) -> 73.5
A7: Retenciones de IRPF que te han hecho | B7: =SUMIFS(Facturas!$H$6:$H$205,Facturas!$M$6:$M$205,Ajustes!$B$3,Facturas!$N$6:$N$205,B$4) -> 0 | C7: =SUMIFS(Facturas!$H$6:$H$205,Facturas!$M$6:$M$205,Ajustes!$B$3,Facturas!$N$6:$N$205,C$4) -> 0 | D7: =SUMIFS(Facturas!$H$6:$H$205,Facturas!$M$6:$M$205,Ajustes!$B$3,Facturas!$N$6:$N$205,D$4) -> 0 | E7: =SUMIFS(Facturas!$H$6:$H$205,Facturas!$M$6:$M$205,Ajustes!$B$3,Facturas!$N$6:$N$205,E$4) -> 24.5 | F7: =SUM(B7:E7) -> 24.5
A8: Cobrado de clientes (neto de retenciones) | B8: =SUMIFS(Facturas!$I$6:$I$205,Facturas!$M$6:$M$205,Ajustes!$B$3,Facturas!$N$6:$N$205,B$4) -> 0 | C8: =SUMIFS(Facturas!$I$6:$I$205,Facturas!$M$6:$M$205,Ajustes!$B$3,Facturas!$N$6:$N$205,C$4) -> 0 | D8: =SUMIFS(Facturas!$I$6:$I$205,Facturas!$M$6:$M$205,Ajustes!$B$3,Facturas!$N$6:$N$205,D$4) -> 0 | E8: =SUMIFS(Facturas!$I$6:$I$205,Facturas!$M$6:$M$205,Ajustes!$B$3,Facturas!$N$6:$N$205,E$4) -> 399 | F8: =SUM(B8:E8) -> 399
A9: Gastos deducibles (base) | B9: =SUMIFS(Gastos!$D$6:$D$205,Gastos!$H$6:$H$205,Ajustes!$B$3,Gastos!$I$6:$I$205,B$4,Gastos!$F$6:$F$205,"Sí") -> 0 | C9: =SUMIFS(Gastos!$D$6:$D$205,Gastos!$H$6:$H$205,Ajustes!$B$3,Gastos!$I$6:$I$205,C$4,Gastos!$F$6:$F$205,"Sí") -> 0 | D9: =SUMIFS(Gastos!$D$6:$D$205,Gastos!$H$6:$H$205,Ajustes!$B$3,Gastos!$I$6:$I$205,D$4,Gastos!$F$6:$F$205,"Sí") -> 0 | E9: =SUMIFS(Gastos!$D$6:$D$205,Gastos!$H$6:$H$205,Ajustes!$B$3,Gastos!$I$6:$I$205,E$4,Gastos!$F$6:$F$205,"Sí") -> 92 | F9: =SUM(B9:E9) -> 92
A10: IVA pagado en gastos (soportado) | B10: =SUMIFS(Gastos!$E$6:$E$205,Gastos!$H$6:$H$205,Ajustes!$B$3,Gastos!$I$6:$I$205,B$4,Gastos!$F$6:$F$205,"Sí") -> 0 | C10: =SUMIFS(Gastos!$E$6:$E$205,Gastos!$H$6:$H$205,Ajustes!$B$3,Gastos!$I$6:$I$205,C$4,Gastos!$F$6:$F$205,"Sí") -> 0 | D10: =SUMIFS(Gastos!$E$6:$E$205,Gastos!$H$6:$H$205,Ajustes!$B$3,Gastos!$I$6:$I$205,D$4,Gastos!$F$6:$F$205,"Sí") -> 0 | E10: =SUMIFS(Gastos!$E$6:$E$205,Gastos!$H$6:$H$205,Ajustes!$B$3,Gastos!$I$6:$I$205,E$4,Gastos!$F$6:$F$205,"Sí") -> 2.52 | F10: =SUM(B10:E10) -> 2.52
A11: Gastos pagados (total, con IVA) | B11: =SUMIFS(Gastos!$G$6:$G$205,Gastos!$H$6:$H$205,Ajustes!$B$3,Gastos!$I$6:$I$205,B$4) -> 0 | C11: =SUMIFS(Gastos!$G$6:$G$205,Gastos!$H$6:$H$205,Ajustes!$B$3,Gastos!$I$6:$I$205,C$4) -> 0 | D11: =SUMIFS(Gastos!$G$6:$G$205,Gastos!$H$6:$H$205,Ajustes!$B$3,Gastos!$I$6:$I$205,D$4) -> 0 | E11: =SUMIFS(Gastos!$G$6:$G$205,Gastos!$H$6:$H$205,Ajustes!$B$3,Gastos!$I$6:$I$205,E$4) -> 94.52 | F11: =SUM(B11:E11) -> 94.52
A12: Impuestos
A13: IVA a ingresar (modelo 303) | B13: =B6-B10 -> 0 | C13: =C6-C10 -> 0 | D13: =D6-D10 -> 0 | E13: =E6-E10 -> 70.98 | F13: =SUM(B13:E13) -> 70.98
A14: Rendimiento neto del trimestre | B14: =B5-B9 -> 0 | C14: =C5-C9 -> 0 | D14: =D5-D9 -> 0 | E14: =E5-E9 -> 258 | F14: =SUM(B14:E14) -> 258
A15: Rendimiento neto acumulado del año | B15: =SUM($B14:B14) -> 0 | C15: =SUM($B14:C14) -> 0 | D15: =SUM($B14:D14) -> 0 | E15: =SUM($B14:E14) -> 258 | F15: =E15 -> 258
A16: Retenciones acumuladas del año | B16: =SUM($B7:B7) -> 0 | C16: =SUM($B7:C7) -> 0 | D16: =SUM($B7:D7) -> 0 | E16: =SUM($B7:E7) -> 24.5 | F16: =E16 -> 24.5
A17: Pago fraccionado IRPF (modelo 130) | B17: =IF(Ajustes!$B$6="Sí",MAX(0,ROUND(Ajustes!$B$5*B15-B16-0,2)),0) -> 0 | C17: =IF(Ajustes!$B$6="Sí",MAX(0,ROUND(Ajustes!$B$5*C15-C16-SUM($B17:B17),2)),0) -> 0 | D17: =IF(Ajustes!$B$6="Sí",MAX(0,ROUND(Ajustes!$B$5*D15-D16-SUM($B17:C17),2)),0) -> 0 | E17: =IF(Ajustes!$B$6="Sí",MAX(0,ROUND(Ajustes!$B$5*E15-E16-SUM($B17:D17),2)),0) -> 27.1 | F17: =SUM(B17:E17) -> 27.1
A18: TOTAL a ingresar en Hacienda este trimestre | B18: =B13+B17 -> 0 | C18: =C13+C17 -> 0 | D18: =D13+D17 -> 0 | E18: =E13+E17 -> 98.08 | F18: =SUM(B18:E18) -> 98.08
A19: Fecha límite | B19: 20 abril | C19: 20 julio | D19: 20 octubre | E19: 30 enero (año sig.)
A20: Dinero que te queda (estimado) | B20: =B8-B11-B13-B17 -> 0 | C20: =C8-C11-C13-C17 -> 0 | D20: =D8-D11-D13-D17 -> 0 | E20: =E8-E11-E13-E17 -> 206.4 | F20: =SUM(B20:E20) -> 206.4
A22: IVA a ingresar negativo = IVA a compensar en próximos trimestres. «Dinero que te queda» ya descuenta IVA, IRPF adelantado, retenciones y gastos.
A23: Estimación orientativa: no incluye deducciones adicionales ni la declaración de la renta anual.
